afluent/__init__.py
afluent/line.py
afluent/main.py
afluent/proj_file.py
afluent/spectrum_parser.py
afluent/tiebreak_generator.py
afluent-0.2.0.dist-info/entry_points.txt
afluent-0.2.0.dist-info/LICENSE
afluent-0.2.0.dist-info/WHEEL
afluent-0.2.0.dist-info/METADATA
afluent-0.2.0.dist-info/RECORD
